Metadata-Version: 2.1
Name: sms365
Version: 1.0
Summary: 365SMS API Client
Author-email: ermalajsonga@gmail.com
